sphae/__init__.py
sphae/__main__.py
sphae/sphae.CITATION
sphae/sphae.LICENSE
sphae/sphae.VERSION
sphae/config/config.yaml
sphae/workflow/Snakefile
sphae/workflow/Snakefile-annot
sphae/workflow/install.smk
sphae/workflow/envs/checkv.yaml
sphae/workflow/envs/filtlong.yaml
sphae/workflow/envs/flye.yaml
sphae/workflow/envs/graph.yaml
sphae/workflow/envs/medaka.yaml
sphae/workflow/envs/megahit.yaml
sphae/workflow/envs/pharokka.yaml
sphae/workflow/envs/phold.yaml
sphae/workflow/envs/phynteny.yaml
sphae/workflow/envs/qc.yaml
sphae/workflow/envs/rasusa.yaml
sphae/workflow/envs/samtools.yaml
sphae/workflow/envs/trees.yaml
sphae/workflow/envs/viralverify.yaml
sphae/workflow/rules/1.preflight-annot.smk
sphae/workflow/rules/1.preflight.smk
sphae/workflow/rules/10.final-reporting.smk
sphae/workflow/rules/10.trees.smk
sphae/workflow/rules/2.targets-annot.smk
sphae/workflow/rules/2.targets.smk
sphae/workflow/rules/3.qc_qa.smk
sphae/workflow/rules/4.assembly.smk
sphae/workflow/rules/4.assembly_no_medaka.smk
sphae/workflow/rules/5.checkv.smk
sphae/workflow/rules/5.components.smk
sphae/workflow/rules/5.viralverify.smk
sphae/workflow/rules/6.phage_genome.smk
sphae/workflow/rules/6.stat_join.smk
sphae/workflow/rules/7.pharokka.smk
sphae/workflow/rules/789.annot.smk
sphae/workflow/rules/8.phold.smk
sphae/workflow/rules/9.phynteny.smk
sphae/workflow/scripts/components.py
sphae/workflow/scripts/fastg2gfa
sphae/workflow/scripts/get_marker_genes.py
sphae/workflow/scripts/joining_stats.py
sphae/workflow/scripts/pick_phage_contigs.py
sphae/workflow/scripts/split_fasta.py
sphae/workflow/scripts/summary-annot.py
sphae/workflow/scripts/summary.py
sphae/workflow/scripts/summary_annot_functions.py
sphae/workflow/scripts/summary_functions.py
sphae/workflow/scripts/graph_utils/build_utils.py
sphae/workflow/scripts/roblib/__init__.py
sphae/workflow/scripts/roblib/alignments.py
sphae/workflow/scripts/roblib/bcolors.py
sphae/workflow/scripts/roblib/blast.py
sphae/workflow/scripts/roblib/colours.py
sphae-1.5.2.dist-info/licenses/LICENSE
sphae-1.5.2.dist-info/METADATA
sphae-1.5.2.dist-info/WHEEL
sphae-1.5.2.dist-info/entry_points.txt
sphae-1.5.2.dist-info/top_level.txt
sphae-1.5.2.dist-info/RECORD
