Metadata-Version: 2.4
Name: sphae
Version: 1.5.2
Summary: Phage workflow
Author-email: Bhavya Papudeshi <npbhavya13@gmail.com>
License: MIT
Keywords: phage,phage therapy,bioinformatics,microbiology,genome,genomics
Classifier: Environment :: Console
Classifier: Environment :: MacOS X
Classifier: Intended Audience :: Science/Research
Classifier: License :: OSI Approved :: MIT License
Classifier: Natural Language :: English
Classifier: Operating System :: POSIX :: Linux
Classifier: Programming Language :: Python :: 3.12
Classifier: Programming Language :: Python :: 3.13
Classifier: Topic :: Scientific/Engineering :: Bio-Informatics
Requires-Python: >=3.9
License-File: LICENSE
Requires-Dist: snaketool-utils>=0.0.5
Requires-Dist: snakemake>=8.28.0
Requires-Dist: pyyaml>=6.0
Requires-Dist: Click==8.1.3
Requires-Dist: metasnek>=0.0.8
Requires-Dist: attrmap>=0.0.7
Requires-Dist: biopython>=1.8.1
Requires-Dist: pandas
Requires-Dist: matplotlib
Requires-Dist: snakemake-executor-plugin-slurm>=0.5.1
Dynamic: license-file
